rai/__init__.py
rai/agents/__init__.py
rai/agents/base.py
rai/agents/integrations/__init__.py
rai/agents/integrations/streamlit.py
rai/agents/langchain/__init__.py
rai/agents/langchain/agent.py
rai/agents/langchain/callback.py
rai/agents/langchain/core/__init__.py
rai/agents/langchain/core/conversational_agent.py
rai/agents/langchain/core/megamind.py
rai/agents/langchain/core/plan_agent.py
rai/agents/langchain/core/react_agent.py
rai/agents/langchain/core/state_based_agent.py
rai/agents/langchain/core/structured_output_agent.py
rai/agents/langchain/core/tool_runner.py
rai/agents/langchain/invocation_helpers.py
rai/agents/langchain/react_agent.py
rai/agents/langchain/state_based_agent.py
rai/agents/ros2/__init__.py
rai/agents/ros2/state_based_agent.py
rai/agents/runner.py
rai/aggregators/__init__.py
rai/aggregators/base.py
rai/aggregators/ros2/__init__.py
rai/aggregators/ros2/aggregators.py
rai/communication/__init__.py
rai/communication/base_connector.py
rai/communication/hri_connector.py
rai/communication/ros2/__init__.py
rai/communication/ros2/api/__init__.py
rai/communication/ros2/api/action.py
rai/communication/ros2/api/base.py
rai/communication/ros2/api/conversion.py
rai/communication/ros2/api/service.py
rai/communication/ros2/api/topic.py
rai/communication/ros2/connectors/__init__.py
rai/communication/ros2/connectors/action_mixin.py
rai/communication/ros2/connectors/base.py
rai/communication/ros2/connectors/hri_connector.py
rai/communication/ros2/connectors/ros2_connector.py
rai/communication/ros2/connectors/service_mixin.py
rai/communication/ros2/context.py
rai/communication/ros2/messages.py
rai/communication/ros2/ros_async.py
rai/communication/ros2/ros_logs.py
rai/communication/ros2/waiters.py
rai/frontend/__init__.py
rai/frontend/configurator.py
rai/frontend/streamlit.py
rai/initialization/__init__.py
rai/initialization/config_initialization.py
rai/initialization/model_initialization.py
rai/messages/__init__.py
rai/messages/artifacts.py
rai_core-2.6.0.dist-info/METADATA
rai_core-2.6.0.dist-info/WHEEL
rai_core-2.6.0.dist-info/entry_points.txt
rai_core-2.6.0.dist-info/RECORD
