Metadata-Version: 2.3
Name: rai_core
Version: 2.6.0
Summary: Core functionality for RAI framework
Author: Maciej Majek
Author-email: maciej.majek@robotec.ai
Requires-Python: >=3.10,<3.13
Classifier: Development Status :: 4 - Beta
Classifier: License :: OSI Approved :: Apache Software License
Classifier: Programming Language :: Python :: 3
Classifier: Programming Language :: Python :: 3.10
Classifier: Programming Language :: Python :: 3.11
Classifier: Programming Language :: Python :: 3.12
Requires-Dist: coloredlogs (>=15.0.1,<16.0.0)
Requires-Dist: deprecated (>=1.2.14,<2.0.0)
Requires-Dist: langchain
Requires-Dist: langchain-aws
Requires-Dist: langchain-community
Requires-Dist: langchain-core (>=0.3,<0.4)
Requires-Dist: langchain-ollama (>=0.3.4,<0.4.0)
Requires-Dist: langchain-openai
Requires-Dist: langfuse (>=2.60.2,<3.0.0)
Requires-Dist: langgraph
Requires-Dist: langgraph-prebuilt
Requires-Dist: lark (>=1.1.9,<2.0.0)
Requires-Dist: numpy (<2.0)
Requires-Dist: opencv-python (>=4.9.0.80,<5.0.0.0)
Requires-Dist: pillow (>=11.0.0,<12.0.0)
Requires-Dist: pydub (>=0.25.1,<0.26.0)
Requires-Dist: requests (>=2.32.2,<3.0.0)
Requires-Dist: streamlit (>=1.44,<2.0)
Requires-Dist: tomli (>=2.0.1,<3.0.0)
Requires-Dist: tomli-w (>=1.1.0,<2.0.0)
Requires-Dist: tqdm (>=4.66.4,<5.0.0)
Requires-Dist: transforms3d (>=0.4.1,<0.5.0)
